dash_jsmole/DashJsmole.py
dash_jsmole/__init__.py
dash_jsmole/_imports_.py
dash_jsmole/dash_jsmole.min.js
dash_jsmole/dash_jsmole.min.js.map
dash_jsmole/metadata.json
dash_jsmole/package-info.json
dash_jsmole-0.0.1.dist-info/LICENSE
dash_jsmole-0.0.1.dist-info/METADATA
dash_jsmole-0.0.1.dist-info/WHEEL
dash_jsmole-0.0.1.dist-info/top_level.txt
dash_jsmole-0.0.1.dist-info/RECORD
