Metadata-Version: 2.1
Name: dash-jsmole
Version: 0.0.1
Summary: jsme editor
Home-page: https://github.com/innoWADEtech/dash-jsmole
Author: innoWADEtech <innoWADEtech@gmail.com>
License: MIT
Platform: UNKNOWN
Classifier: Framework :: Dash
License-File: LICENSE
